mathsoperrations/__init__.py
mathsoperrations/operrations.py
mathematical_operations-0.0.1.dist-info/METADATA
mathematical_operations-0.0.1.dist-info/WHEEL
mathematical_operations-0.0.1.dist-info/top_level.txt
mathematical_operations-0.0.1.dist-info/RECORD
