Metadata-Version: 2.1
Name: mathematical_operations
Version: 0.0.1
Summary: Basic Mathematical operations.
Author: Lesin (Student at iiit banglore)
Author-email: <lesin280204@gmail.com>
Keywords: python,basic math,iiit banglore
Classifier: Development Status :: 1 - Planning
Classifier: Intended Audience :: Developers
Classifier: Programming Language :: Python :: 3
Classifier: Operating System :: Unix
Classifier: Operating System :: MacOS :: MacOS X
Classifier: Operating System :: Microsoft :: Windows
